pydent/.idea/.gitignore
pydent/.idea/inspectionProfiles/profiles_settings.xml
pydent/.idea/libraries/R_User_Library.xml
pydent/.idea/misc.xml
pydent/.idea/modules.xml
pydent/.idea/pydent.iml
pydent/.idea/vcs.xml
pydent/__init__.py
pydent/__version__.py
pydent/aqhttp.py
pydent/aql/__init__.py
pydent/aql/aql.schema.json
pydent/aqsession.py
pydent/base.py
pydent/browser.py
pydent/exceptions.py
pydent/interfaces.py
pydent/inventory_updater.py
pydent/marshaller/__init__.py
pydent/marshaller/base.py
pydent/marshaller/descriptors.py
pydent/marshaller/exceptions.py
pydent/marshaller/fields.py
pydent/marshaller/registry.py
pydent/marshaller/schema.py
pydent/marshaller/utils.py
pydent/models/__init__.py
pydent/models/code.py
pydent/models/controller_mixin.py
pydent/models/crud_mixin.py
pydent/models/data_associations.py
pydent/models/field_value.py
pydent/models/field_value_mixins.py
pydent/models/inventory.py
pydent/models/job.py
pydent/models/operation.py
pydent/models/plan.py
pydent/models/sample.py
pydent/models/user.py
pydent/planner/__init__.py
pydent/planner/graph.py
pydent/planner/plan_optimizer.py
pydent/planner/planner.py
pydent/planner/utils.py
pydent/relationships.py
pydent/sessionabc.py
pydent/utils/__init__.py
pydent/utils/async_requests.py
pydent/utils/loggable/__init__.py
pydent/utils/logging_helpers.py
pydent/utils/matrix_mapper.py
pydent/utils/query_builder.py
pydent-1.0.11.dist-info/LICENSE
pydent-1.0.11.dist-info/WHEEL
pydent-1.0.11.dist-info/METADATA
pydent-1.0.11.dist-info/RECORD
