Metadata-Version: 2.1
Name: pydent
Version: 1.0.11
Summary: Aquarium's Python API for planning, executing, and analyzing scientific experiments.
Home-page: https://www.github.com/aquariumbio/trident
License: MIT
Author: jvrana
Author-email: justin.vrana@gmail.com
Requires-Python: >=3.6,<4.0
Classifier: License :: OSI Approved :: MIT License
Classifier: Programming Language :: Python :: 3
Classifier: Programming Language :: Python :: 3.6
Classifier: Programming Language :: Python :: 3.7
Classifier: Programming Language :: Python :: 3.8
Classifier: Programming Language :: Python :: 3.9
Requires-Dist: colorlog (>=4.0,<5.0)
Requires-Dist: inflection (>=0.3.1,<0.4.0)
Requires-Dist: jsonschema (>=3.2.0,<4.0.0)
Requires-Dist: nest-asyncio (>=1.0,<2.0)
Requires-Dist: networkx (>=2.3,<3.0)
Requires-Dist: requests (>=2.22,<3.0)
Requires-Dist: retry (>=0.9.2,<0.10.0)
Requires-Dist: tqdm (>=4.32,<5.0)
Project-URL: Documentation, http://aquariumbio.github.io/trident
Project-URL: Repository, https://www.github.com/aquariumbio/trident
